bq_mcp_server/__init__.py
bq_mcp_server/adapters/__init__.py
bq_mcp_server/adapters/mcp_server.py
bq_mcp_server/adapters/web.py
bq_mcp_server/core/__init__.py
bq_mcp_server/core/async_funcs.py
bq_mcp_server/core/converter.py
bq_mcp_server/core/entities.py
bq_mcp_server/core/file_exporter.py
bq_mcp_server/core/logic_base.py
bq_mcp_server/core/query_parser.py
bq_mcp_server/repositories/__init__.py
bq_mcp_server/repositories/bigquery_client.py
bq_mcp_server/repositories/cache_manager.py
bq_mcp_server/repositories/config.py
bq_mcp_server/repositories/log.py
bq_mcp_server/repositories/logic.py
bq_mcp_server/repositories/query_executor.py
bq_mcp_server/repositories/search_engine.py
bq_mcp_server-0.2.2.dist-info/METADATA
bq_mcp_server-0.2.2.dist-info/WHEEL
bq_mcp_server-0.2.2.dist-info/entry_points.txt
bq_mcp_server-0.2.2.dist-info/licenses/LICENSE
bq_mcp_server-0.2.2.dist-info/RECORD
