Metadata-Version: 2.4
Name: bq_mcp_server
Version: 0.2.2
Summary: Python-based MCP (Model Context Protocol) server that retrieves dataset, table, and schema information from Google Cloud BigQuery
Project-URL: Homepage, https://github.com/takada-at/bq_mcp_server
Author-email: takada-at <takada-at@klab.com>
License: Copyright 2025 takada-at
License-File: LICENSE
Requires-Python: >=3.10
Requires-Dist: fastapi>=0.115.12
Requires-Dist: gcloud-aio-bigquery>=7.1.0
Requires-Dist: google-cloud-bigquery>=3.31.0
Requires-Dist: mcp[cli]==1.12.3
Requires-Dist: pydantic>=2.11.3
Requires-Dist: python-dotenv>=1.1.0
